losoto/__init__.py
losoto/_importer.py
losoto/_logging.py
losoto/_version.py
losoto/h5parm.py
losoto/lib_losoto.py
losoto/lib_operations.py
losoto/lib_unwrap.py
losoto/phase_colormap.py
losoto/operations/__init__.py
losoto/operations/_faraday_timestep.py
losoto/operations/_fitClockTEC.py
losoto/operations/abs.py
losoto/operations/clip.py
losoto/operations/clocktec.py
losoto/operations/deleteaxis.py
losoto/operations/duplicate.py
losoto/operations/faraday.py
losoto/operations/flag.py
losoto/operations/flagextend.py
losoto/operations/flagstation.py
losoto/operations/interpolate.py
losoto/operations/interpolatedirections.py
losoto/operations/lofarbeam.py
losoto/operations/norm.py
losoto/operations/plot.py
losoto/operations/polalign.py
losoto/operations/reference.py
losoto/operations/replicateonaxis.py
losoto/operations/reset.py
losoto/operations/residuals.py
losoto/operations/reweight.py
losoto/operations/smooth.py
losoto/operations/structure.py
losoto/operations/tec.py
losoto-2.6.0.data/scripts/H5parm2parmdb.py
losoto-2.6.0.data/scripts/H5parm_collector.py
losoto-2.6.0.data/scripts/H5parm_copy.py
losoto-2.6.0.data/scripts/H5parm_interpolator.py
losoto-2.6.0.data/scripts/H5parm_split.py
losoto-2.6.0.data/scripts/killMS2H5parm.py
losoto-2.6.0.data/scripts/losoto
losoto-2.6.0.data/scripts/parmdb2H5parm.py
losoto-2.6.0.dist-info/licenses/LICENSE
losoto-2.6.0.dist-info/METADATA
losoto-2.6.0.dist-info/WHEEL
losoto-2.6.0.dist-info/top_level.txt
losoto-2.6.0.dist-info/RECORD
