Metadata-Version: 2.4
Name: losoto
Version: 2.6.0
Summary: LOFAR Solution Tool
Author-email: Francesco Gasperin <rev@voo.it>, David Rafferty <drafferty@hs.uni-hamburg.de>
Maintainer-email: Marcel Loose <loose@astron.nl>
License-Expression: GPL-3.0-or-later
Keywords: LOFAR,astronomy,radio astronomy,data analysis
Classifier: Development Status :: 5 - Production/Stable
Classifier: Intended Audience :: Science/Research
Classifier: Natural Language :: English
Classifier: Operating System :: POSIX :: Linux
Classifier: Programming Language :: Python :: 3
Classifier: Topic :: Scientific/Engineering :: Astronomy
Classifier: Topic :: Software Development :: Libraries :: Python Modules
Requires-Python: >=3.10
License-File: LICENSE
Requires-Dist: lofar-parameterset>=1.1
Requires-Dist: matplotlib
Requires-Dist: numpy
Requires-Dist: progressbar
Requires-Dist: python-casacore>=3.0
Requires-Dist: scipy
Requires-Dist: tables>=3.4
Provides-Extra: test
Requires-Dist: tox; extra == "test"
Dynamic: license-file
